yxalign/__init__.py
yxalign/versions.py
yxalign/src/__init__.py
yxalign/src/blast.py
yxalign/src/psl.py
yxalign-0.0.1.dist-info/LICENSE
yxalign-0.0.1.dist-info/METADATA
yxalign-0.0.1.dist-info/WHEEL
yxalign-0.0.1.dist-info/top_level.txt
yxalign-0.0.1.dist-info/RECORD
