Metadata-Version: 2.1
Name: yxalign
Version: 0.0.1
Summary: Here's an example of a repository
Home-page: https://github.com/SouthernCD/yxalign
Author: Yuxing Xu
Author-email: xuyuxing@mail.kib.ac.cn
Requires-Python: >=3.5
License-File: LICENSE
Requires-Dist: yxutil >=0.0.3
Requires-Dist: yxseq
Requires-Dist: yxsql
Requires-Dist: yxmath
Requires-Dist: lxml >=5.3.0
